pips/__init__.py
pips/__main__.py
pips/cli.py
pips/constants.py
pips/crawl.py
pips/pip.py
pips/verifier.py
pipsamo-0.3.0.dist-info/LICENSE
pipsamo-0.3.0.dist-info/METADATA
pipsamo-0.3.0.dist-info/WHEEL
pipsamo-0.3.0.dist-info/entry_points.txt
pipsamo-0.3.0.dist-info/top_level.txt
pipsamo-0.3.0.dist-info/RECORD
