Metadata-Version: 2.1
Name: pipsamo
Version: 0.3.0
Summary: Pips Installs Packages Securely
Home-page: https://github.com/samocorp/pips
Author: samo
Author-email: thesamogroup@gmail.com
License: MIT
Keywords: python,pip,pips,security
Platform: UNKNOWN
Classifier: Intended Audience :: Developers
Classifier: Operating System :: OS Independent
Classifier: Programming Language :: Python
Classifier: Programming Language :: Python :: 2
Classifier: Programming Language :: Python :: 2.7
Classifier: Programming Language :: Python :: 3
Classifier: Programming Language :: Python :: 3.6
Classifier: Programming Language :: Python :: 3.7
Classifier: Programming Language :: Python :: 3.8
Classifier: Topic :: Software Development :: Libraries
Classifier: Topic :: Software Development :: Libraries :: Python Modules
License-File: LICENSE
Requires-Dist: requests
Requires-Dist: superprocessor
Requires-Dist: pypistats
Requires-Dist: pyaml
Requires-Dist: toml
